{
  "comments": [],
  "orders": [],
  "tickets": [],
  "users":[
    {
      "id": 1,
      "name": "emad",
      "lastName": "maleki",
      "email": "emadmaleki84@gmail.com",
      "password": "123456789",
      "age": "16",
      "gender": "",
      "status": true,
      "admin": true,
      "img": "/images/users/ava-1.jpg",
      "phone": "09149988816",
      "joinDate": "1401/4/2",
      "likes": [],
      "address": "adresssss"
    }
  ],
  "categories": [
    {
      "id": 1,
      "name": "apple",
      "desc": "this is test!",
      "img": "/images/products/huawei.png"
    },
    {
      "id": 2,
      "name": "samsung",
      "desc": "this is test!",
      "img": "/images/products/samsung.png"
    },
    {
      "id": 3,
      "name": "xiaomi",
      "desc": "this is test!",
      "img": "/images/products/xiaomi.png"
    },
    {
      "id": 5,
      "name": "huawei",
      "desc": "this is test!",
      "img": "/images/products/huawei.png"
    }
  ],
  "products": [
    {
      "id": 1,
      "title": "xhuawei nova 9 SE",
      "price": 300,
      "image01": "/images/products/1.png",
      "image02": "/images/products/2.png",
      "image03": "/images/products/3.png",
      "category": "huawei",
      "colors": [
        {
          "name": "blue",
          "price": 10
        },
        {
          "name": "green",
          "price": 5
        },
        {
          "name": "black",
          "price": 8
        }
      ],
      "config": {
        "ram": [
          {
            "value": "2g",
            "price": 9
          },
          {
            "value": "4g",
            "price": 11
          },
          {
            "value": "6g",
            "price": 15
          }
        ],
        "memory": "128",
        "material": "metal",
        "camera": "108mp",
        "battery": "4000 mAh",
        "display": "6.7",
        "internet": "5G"
      },
      "desc": "Lorem ipsum dolor sit amet consectetur adipisicing elit. Labore rerum laboriosam delectus ipsum doloremque eius expedita quis dolore. Accusamus ipsum nobis incidunt iure inventore aliquam, ullam autem quaerat, quas quasi nam excepturi maiores suscipit. Officia ratione fugit nam possimus assumenda qui aliquam totam voluptatum veniam! Incidunt deleniti totam reprehenderit, quasi cumque consectetur. Laboriosam ab nobis ratione. Sequi quia vitae, similique quod officiis sint adipisci voluptatum fugit assumenda quos accusamus numquam quisquam architecto ratione cum tenetur libero. Amet numquam sequi impedit obcaecati ducimus, fugit labore fuga dolorem quisquam. Itaque quisquam nostrum iste praesentium beatae voluptas inventore, voluptatibus, sapiente, quidem doloremque assumenda! ",
      "created_at": "2022/8/22",
      "quantity": 1
    },
    {
      "id": 2,
      "title": "xhuawei nova 9",
      "price": 500,
      "image01": "/images/products/4.png",
      "image02": "/images/products/5.png",
      "image03": "/images/products/6.png",
      "category": "huawei",
      "colors": [
        {
          "name": "blue",
          "price": 10
        },
        {
          "name": "green",
          "price": 5
        },
        {
          "name": "black",
          "price": 8
        }
      ],
      "config": {
        "ram": [
          {
            "value": "2g",
            "price": 9
          },
          {
            "value": "4g",
            "price": 11
          },
          {
            "value": "6g",
            "price": 15
          }
        ],
        "memory": "128",
        "material": "metal",
        "camera": "108mp",
        "battery": "4000 mAh",
        "display": "6.7",
        "internet": "4G"
      },
      "desc": "Lorem ipsum dolor sit amet consectetur adipisicing elit. Labore rerum laboriosam delectus ipsum doloremque eius expedita quis dolore. Accusamus ipsum nobis incidunt iure inventore aliquam, ullam autem quaerat, quas quasi nam excepturi maiores suscipit. Officia ratione fugit nam possimus assumenda qui aliquam totam voluptatum veniam! Incidunt deleniti totam reprehenderit, quasi cumque consectetur. Laboriosam ab nobis ratione. Sequi quia vitae, similique quod officiis sint adipisci voluptatum fugit assumenda quos accusamus numquam quisquam architecto ratione cum tenetur libero. Amet numquam sequi impedit obcaecati ducimus, fugit labore fuga dolorem quisquam. Itaque quisquam nostrum iste praesentium beatae voluptas inventore, voluptatibus, sapiente, quidem doloremque assumenda! ",
      "created_at": "2022/8/23",
      "quantity": 1
    },
    {
      "id": 3,
      "title": "xhuawei p50 pro",
      "price": 300,
      "image01": "/images/products/7.png",
      "image02": "/images/products/8.png",
      "image03": "/images/products/9.png",
      "category": "huawei",
      "colors": [
        {
          "name": "red",
          "price": 10
        },
        {
          "name": "green",
          "price": 5
        },
        {
          "name": "black",
          "price": 8
        }
      ],
      "config": {
        "ram": [
          {
            "value": "2g",
            "price": 5
          },
          {
            "value": "4g",
            "price": 14
          },
          {
            "value": "6g",
            "price": 9
          }
        ],
        "memory": "256",
        "material": "metal",
        "camera": "108mp",
        "battery": "3000 mAh",
        "display": "6.5",
        "internet": "5G"
      },
      "desc": "Lorem ipsum dolor sit amet consectetur adipisicing elit. Labore rerum laboriosam delectus ipsum doloremque eius expedita quis dolore. Accusamus ipsum nobis incidunt iure inventore aliquam, ullam autem quaerat, quas quasi nam excepturi maiores suscipit. Officia ratione fugit nam possimus assumenda qui aliquam totam voluptatum veniam! Incidunt deleniti totam reprehenderit, quasi cumque consectetur. Laboriosam ab nobis ratione. Sequi quia vitae, similique quod officiis sint adipisci voluptatum fugit assumenda quos accusamus numquam quisquam architecto ratione cum tenetur libero. Amet numquam sequi impedit obcaecati ducimus, fugit labore fuga dolorem quisquam. Itaque quisquam nostrum iste praesentium beatae voluptas inventore, voluptatibus, sapiente, quidem doloremque assumenda! ",
      "created_at": "2022/5/22",
      "quantity": 1
    },
    {
      "id": 4,
      "title": "iphone 11",
      "price": 1000,
      "image01": "/images/products/iphone-11-green.png",
      "image02": "/images/products/iphone-11-purple.png",
      "image03": "/images/products/iphone-11-red.png",
      "category": "iphone",
      "colors": [
        {
          "name": "red",
          "price": 10
        },
        {
          "name": "green",
          "price": 5
        },
        {
          "name": "black",
          "price": 8
        }
      ],
      "config": {
        "ram": [
          {
            "value": "2g",
            "price": 9
          },
          {
            "value": "4g",
            "price": 11
          },
          {
            "value": "6g",
            "price": 15
          }
        ],
        "memory": "64",
        "material": "metal",
        "camera": "108mp",
        "battery": "4000 mAh",
        "display": "6.7",
        "internet": "5G"
      },
      "desc": "Lorem ipsum dolor sit amet consectetur adipisicing elit. Labore rerum laboriosam delectus ipsum doloremque eius expedita quis dolore. Accusamus ipsum nobis incidunt iure inventore aliquam, ullam autem quaerat, quas quasi nam excepturi maiores suscipit. Officia ratione fugit nam possimus assumenda qui aliquam totam voluptatum veniam! Incidunt deleniti totam reprehenderit, quasi cumque consectetur. Laboriosam ab nobis ratione. Sequi quia vitae, similique quod officiis sint adipisci voluptatum fugit assumenda quos accusamus numquam quisquam architecto ratione cum tenetur libero. Amet numquam sequi impedit obcaecati ducimus, fugit labore fuga dolorem quisquam. Itaque quisquam nostrum iste praesentium beatae voluptas inventore, voluptatibus, sapiente, quidem doloremque assumenda! ",
      "created_at": "2022/8/22",
      "quantity": 1
    },
    {
      "id": 5,
      "title": "iphone 12 pro max",
      "price": 1200,
      "image01": "/images/products/iphone-12-pro-max-dark-green.png",
      "image02": "/images/products/iphone-12-pro-max-dark-light-green.png",
      "image03": "/images/products/iphone-12-pro-max-dark-purple.png",
      "category": "apple",
      "colors": [
        {
          "name": "blue",
          "price": 10
        },
        {
          "name": "green",
          "price": 5
        },
        {
          "name": "black",
          "price": 8
        }
      ],
      "config": {
        "ram": [
          {
            "value": "2g",
            "price": 9
          },
          {
            "value": "4g",
            "price": 11
          },
          {
            "value": "6g",
            "price": 15
          }
        ],
        "memory": "128",
        "material": "metal",
        "camera": "108mp",
        "battery": "4000 mAh",
        "display": "6.7",
        "internet": "5G"
      },
      "desc": "Lorem ipsum dolor sit amet consectetur adipisicing elit. Labore rerum laboriosam delectus ipsum doloremque eius expedita quis dolore. Accusamus ipsum nobis incidunt iure inventore aliquam, ullam autem quaerat, quas quasi nam excepturi maiores suscipit. Officia ratione fugit nam possimus assumenda qui aliquam totam voluptatum veniam! Incidunt deleniti totam reprehenderit, quasi cumque consectetur. Laboriosam ab nobis ratione. Sequi quia vitae, similique quod officiis sint adipisci voluptatum fugit assumenda quos accusamus numquam quisquam architecto ratione cum tenetur libero. Amet numquam sequi impedit obcaecati ducimus, fugit labore fuga dolorem quisquam. Itaque quisquam nostrum iste praesentium beatae voluptas inventore, voluptatibus, sapiente, quidem doloremque assumenda! ",
      "created_at": "2022/8/22",
      "quantity": 1
    },
    {
      "id": 6,
      "title": "iphone 13 mini",
      "price": 1300,
      "image01": "/images/products/iphone-13-mini-blue.png",
      "image02": "/images/products/iphone-13-mini-pink.png",
      "image03": "/images/products/iphone-13-mini-midnight.png",
      "category": "apple",
      "colors": [
        {
          "name": "blue",
          "price": 10
        },
        {
          "name": "pink",
          "price": 5
        },
        {
          "name": "black",
          "price": 8
        }
      ],
      "config": {
        "ram": [
          {
            "value": "2g",
            "price": 9
          },
          {
            "value": "4g",
            "price": 11
          },
          {
            "value": "6g",
            "price": 15
          }
        ],
        "memory": "128",
        "material": "metal",
        "camera": "108mp",
        "battery": "4000 mAh",
        "display": "6.7",
        "internet": "5G"
      },
      "desc": "Lorem ipsum dolor sit amet consectetur adipisicing elit. Labore rerum laboriosam delectus ipsum doloremque eius expedita quis dolore. Accusamus ipsum nobis incidunt iure inventore aliquam, ullam autem quaerat, quas quasi nam excepturi maiores suscipit. Officia ratione fugit nam possimus assumenda qui aliquam totam voluptatum veniam! Incidunt deleniti totam reprehenderit, quasi cumque consectetur. Laboriosam ab nobis ratione. Sequi quia vitae, similique quod officiis sint adipisci voluptatum fugit assumenda quos accusamus numquam quisquam architecto ratione cum tenetur libero. Amet numquam sequi impedit obcaecati ducimus, fugit labore fuga dolorem quisquam. Itaque quisquam nostrum iste praesentium beatae voluptas inventore, voluptatibus, sapiente, quidem doloremque assumenda! ",
      "created_at": "2022/8/22",
      "quantity": 1
    },
    {
      "id": 7,
      "title": "iphone 13 pro max",
      "price": 1400,
      "image01": "/images/products/iphone-13-pro-max-black.png",
      "image02": "/images/products/iphone-13-pro-max-blue.png",
      "image03": "/images/products/iphone-13-pro-max-white.png",
      "category": "apple",
      "colors": [
        {
          "name": "blue",
          "price": 10
        },
        {
          "name": "green",
          "price": 5
        },
        {
          "name": "black",
          "price": 8
        }
      ],
      "config": {
        "ram": [
          {
            "value": "2g",
            "price": 9
          },
          {
            "value": "4g",
            "price": 11
          },
          {
            "value": "6g",
            "price": 15
          }
        ],
        "memory": "128",
        "material": "metal",
        "camera": "108mp",
        "battery": "4000 mAh",
        "display": "6.7",
        "internet": "5G"
      },
      "desc": "Lorem ipsum dolor sit amet consectetur adipisicing elit. Labore rerum laboriosam delectus ipsum doloremque eius expedita quis dolore. Accusamus ipsum nobis incidunt iure inventore aliquam, ullam autem quaerat, quas quasi nam excepturi maiores suscipit. Officia ratione fugit nam possimus assumenda qui aliquam totam voluptatum veniam! Incidunt deleniti totam reprehenderit, quasi cumque consectetur. Laboriosam ab nobis ratione. Sequi quia vitae, similique quod officiis sint adipisci voluptatum fugit assumenda quos accusamus numquam quisquam architecto ratione cum tenetur libero. Amet numquam sequi impedit obcaecati ducimus, fugit labore fuga dolorem quisquam. Itaque quisquam nostrum iste praesentium beatae voluptas inventore, voluptatibus, sapiente, quidem doloremque assumenda! ",
      "created_at": "2022/8/22",
      "quantity": 1
    },
    {
      "id": 8,
      "title": "iphone SE",
      "price": 300,
      "image01": "/images/products/iphone-SE-midnight-2020.png",
      "image02": "/images/products/iphone-SE-red-2020.png",
      "image03": "/images/products/iphone-SE-white-2020.png",
      "category": "apple",
      "colors": [
        {
          "name": "white",
          "price": 10
        },
        {
          "name": "red",
          "price": 5
        },
        {
          "name": "black",
          "price": 8
        }
      ],
      "config": {
        "ram": [
          {
            "value": "3g",
            "price": 9
          },
          {
            "value": "4g",
            "price": 11
          },
          {
            "value": "6g",
            "price": 15
          }
        ],
        "memory": "64",
        "material": "metal",
        "camera": "108mp",
        "battery": "4000 mAh",
        "display": "5.78",
        "internet": "4G"
      },
      "desc": "Lorem ipsum dolor sit amet consectetur adipisicing elit. Labore rerum laboriosam delectus ipsum doloremque eius expedita quis dolore. Accusamus ipsum nobis incidunt iure inventore aliquam, ullam autem quaerat, quas quasi nam excepturi maiores suscipit. Officia ratione fugit nam possimus assumenda qui aliquam totam voluptatum veniam! Incidunt deleniti totam reprehenderit, quasi cumque consectetur. Laboriosam ab nobis ratione. Sequi quia vitae, similique quod officiis sint adipisci voluptatum fugit assumenda quos accusamus numquam quisquam architecto ratione cum tenetur libero. Amet numquam sequi impedit obcaecati ducimus, fugit labore fuga dolorem quisquam. Itaque quisquam nostrum iste praesentium beatae voluptas inventore, voluptatibus, sapiente, quidem doloremque assumenda! ",
      "created_at": "2022/8/22",
      "quantity": 1
    },
    {
      "id": 9,
      "title": "samsung galaxi note 20 ultra",
      "price": 1500,
      "image01": "/images/products/10.png",
      "image02": "/images/products/11.png",
      "image03": "/images/products/12.png",
      "category": "samsung",
      "colors": [
        {
          "name": "white",
          "price": 17
        },
        {
          "name": "green",
          "price": 5
        },
        {
          "name": "black",
          "price": 8
        }
      ],
      "config": {
        "ram": [
          {
            "value": "2g",
            "price": 9
          },
          {
            "value": "4g",
            "price": 11
          },
          {
            "value": "6g",
            "price": 15
          }
        ],
        "memory": "128",
        "material": "metal",
        "camera": "108mp",
        "battery": "4000 mAh",
        "display": "6.7",
        "internet": "5G"
      },
      "desc": "Lorem ipsum dolor sit amet consectetur adipisicing elit. Labore rerum laboriosam delectus ipsum doloremque eius expedita quis dolore. Accusamus ipsum nobis incidunt iure inventore aliquam, ullam autem quaerat, quas quasi nam excepturi maiores suscipit. Officia ratione fugit nam possimus assumenda qui aliquam totam voluptatum veniam! Incidunt deleniti totam reprehenderit, quasi cumque consectetur. Laboriosam ab nobis ratione. Sequi quia vitae, similique quod officiis sint adipisci voluptatum fugit assumenda quos accusamus numquam quisquam architecto ratione cum tenetur libero. Amet numquam sequi impedit obcaecati ducimus, fugit labore fuga dolorem quisquam. Itaque quisquam nostrum iste praesentium beatae voluptas inventore, voluptatibus, sapiente, quidem doloremque assumenda! ",
      "created_at": "2022/8/22",
      "quantity": 1
    },
    {
      "id": 10,
      "title": "samsung galaxi s22 ultra",
      "price": 300,
      "image01": "/images/products/13.png",
      "image02": "/images/products/14.png",
      "image03": "/images/products/15.png",
      "category": "samsung",
      "colors": [
        {
          "name": "white",
          "price": 10
        },
        {
          "name": "green",
          "price": 5
        },
        {
          "name": "black",
          "price": 8
        }
      ],
      "config": {
        "ram": [
          {
            "value": "2g",
            "price": 9
          },
          {
            "value": "4g",
            "price": 11
          },
          {
            "value": "12g",
            "price": 15
          }
        ],
        "memory": "256",
        "material": "metal",
        "camera": "108mp",
        "battery": "4000 mAh",
        "display": "6.7",
        "internet": "5G"
      },
      "desc": "Lorem ipsum dolor sit amet consectetur adipisicing elit. Labore rerum laboriosam delectus ipsum doloremque eius expedita quis dolore. Accusamus ipsum nobis incidunt iure inventore aliquam, ullam autem quaerat, quas quasi nam excepturi maiores suscipit. Officia ratione fugit nam possimus assumenda qui aliquam totam voluptatum veniam! Incidunt deleniti totam reprehenderit, quasi cumque consectetur. Laboriosam ab nobis ratione. Sequi quia vitae, similique quod officiis sint adipisci voluptatum fugit assumenda quos accusamus numquam quisquam architecto ratione cum tenetur libero. Amet numquam sequi impedit obcaecati ducimus, fugit labore fuga dolorem quisquam. Itaque quisquam nostrum iste praesentium beatae voluptas inventore, voluptatibus, sapiente, quidem doloremque assumenda! ",
      "created_at": "2022/8/22",
      "quantity": 1
    },
    {
      "id": 11,
      "title": "samsung galaxi s20 ultra",
      "price": 1200,
      "image01": "/images/products/16.png",
      "image02": "/images/products/17.png",
      "image03": "/images/products/18.png",
      "category": "samsung",
      "colors": [
        {
          "name": "blue",
          "price": 10
        },
        {
          "name": "green",
          "price": 5
        },
        {
          "name": "black",
          "price": 8
        }
      ],
      "config": {
        "ram": [
          {
            "value": "2g",
            "price": 9
          },
          {
            "value": "4g",
            "price": 11
          },
          {
            "value": "6g",
            "price": 15
          }
        ],
        "memory": "128",
        "material": "metal",
        "camera": "108mp",
        "battery": "4000 mAh",
        "display": "6.7",
        "internet": "5G"
      },
      "desc": "Lorem ipsum dolor sit amet consectetur adipisicing elit. Labore rerum laboriosam delectus ipsum doloremque eius expedita quis dolore. Accusamus ipsum nobis incidunt iure inventore aliquam, ullam autem quaerat, quas quasi nam excepturi maiores suscipit. Officia ratione fugit nam possimus assumenda qui aliquam totam voluptatum veniam! Incidunt deleniti totam reprehenderit, quasi cumque consectetur. Laboriosam ab nobis ratione. Sequi quia vitae, similique quod officiis sint adipisci voluptatum fugit assumenda quos accusamus numquam quisquam architecto ratione cum tenetur libero. Amet numquam sequi impedit obcaecati ducimus, fugit labore fuga dolorem quisquam. Itaque quisquam nostrum iste praesentium beatae voluptas inventore, voluptatibus, sapiente, quidem doloremque assumenda! ",
      "created_at": "2022/8/22",
      "quantity": 1
    },
    {
      "id": 12,
      "title": "samsung galaxi fold",
      "price": 1250,
      "image01": "/images/products/19.png",
      "image02": "/images/products/20.png",
      "image03": "/images/products/21.png",
      "category": "samsung",
      "colors": [
        {
          "name": "blue",
          "price": 10
        },
        {
          "name": "pink",
          "price": 5
        },
        {
          "name": "black",
          "price": 8
        }
      ],
      "config": {
        "ram": [
          {
            "value": "2g",
            "price": 9
          },
          {
            "value": "4g",
            "price": 11
          },
          {
            "value": "6g",
            "price": 15
          }
        ],
        "memory": "128",
        "material": "metal",
        "camera": "108mp",
        "battery": "4000 mAh",
        "display": "6.7",
        "internet": "5G"
      },
      "desc": "Lorem ipsum dolor sit amet consectetur adipisicing elit. Labore rerum laboriosam delectus ipsum doloremque eius expedita quis dolore. Accusamus ipsum nobis incidunt iure inventore aliquam, ullam autem quaerat, quas quasi nam excepturi maiores suscipit. Officia ratione fugit nam possimus assumenda qui aliquam totam voluptatum veniam! Incidunt deleniti totam reprehenderit, quasi cumque consectetur. Laboriosam ab nobis ratione. Sequi quia vitae, similique quod officiis sint adipisci voluptatum fugit assumenda quos accusamus numquam quisquam architecto ratione cum tenetur libero. Amet numquam sequi impedit obcaecati ducimus, fugit labore fuga dolorem quisquam. Itaque quisquam nostrum iste praesentium beatae voluptas inventore, voluptatibus, sapiente, quidem doloremque assumenda! ",
      "created_at": "2022/8/22",
      "quantity": 1
    },
    {
      "id": 13,
      "title": "xiaomi redmi k40 pro gaming",
      "price": 900,
      "image01": "/images/products/22.png",
      "image02": "/images/products/23.png",
      "image03": "/images/products/24.png",
      "category": "xiaomi",
      "colors": [
        {
          "name": "blue",
          "price": 10
        },
        {
          "name": "green",
          "price": 5
        },
        {
          "name": "black",
          "price": 8
        }
      ],
      "config": {
        "ram": [
          {
            "value": "2g",
            "price": 9
          },
          {
            "value": "4g",
            "price": 11
          },
          {
            "value": "12g",
            "price": 15
          }
        ],
        "memory": "128",
        "material": "metal",
        "camera": "108mp",
        "battery": "4000 mAh",
        "display": "6.7",
        "internet": "5G"
      },
      "desc": "Lorem ipsum dolor sit amet consectetur adipisicing elit. Labore rerum laboriosam delectus ipsum doloremque eius expedita quis dolore. Accusamus ipsum nobis incidunt iure inventore aliquam, ullam autem quaerat, quas quasi nam excepturi maiores suscipit. Officia ratione fugit nam possimus assumenda qui aliquam totam voluptatum veniam! Incidunt deleniti totam reprehenderit, quasi cumque consectetur. Laboriosam ab nobis ratione. Sequi quia vitae, similique quod officiis sint adipisci voluptatum fugit assumenda quos accusamus numquam quisquam architecto ratione cum tenetur libero. Amet numquam sequi impedit obcaecati ducimus, fugit labore fuga dolorem quisquam. Itaque quisquam nostrum iste praesentium beatae voluptas inventore, voluptatibus, sapiente, quidem doloremque assumenda! ",
      "created_at": "2022/8/22",
      "quantity": 1
    },
    {
      "id": 20,
      "title": "xiaomi 12X",
      "price": 950,
      "image01": "/images/products/25.png",
      "image02": "/images/products/26.png",
      "image03": "/images/products/27.png",
      "category": "xiaomi",
      "colors": [
        {
          "name": "blue",
          "price": 10
        },
        {
          "name": "green",
          "price": 5
        },
        {
          "name": "black",
          "price": 8
        }
      ],
      "config": {
        "ram": [
          {
            "value": "2g",
            "price": 9
          },
          {
            "value": "4g",
            "price": 11
          },
          {
            "value": "6g",
            "price": 15
          }
        ],
        "memory": "128",
        "material": "metal",
        "camera": "108mp",
        "battery": "4000 mAh",
        "display": "6.7",
        "internet": "5G"
      },
      "desc": "Lorem ipsum dolor sit amet consectetur adipisicing elit. Labore rerum laboriosam delectus ipsum doloremque eius expedita quis dolore. Accusamus ipsum nobis incidunt iure inventore aliquam, ullam autem quaerat, quas quasi nam excepturi maiores suscipit. Officia ratione fugit nam possimus assumenda qui aliquam totam voluptatum veniam! Incidunt deleniti totam reprehenderit, quasi cumque consectetur. Laboriosam ab nobis ratione. Sequi quia vitae, similique quod officiis sint adipisci voluptatum fugit assumenda quos accusamus numquam quisquam architecto ratione cum tenetur libero. Amet numquam sequi impedit obcaecati ducimus, fugit labore fuga dolorem quisquam. Itaque quisquam nostrum iste praesentium beatae voluptas inventore, voluptatibus, sapiente, quidem doloremque assumenda! ",
      "created_at": "2022/8/22",
      "quantity": 1
    },
    {
      "id": 14,
      "title": "xiaomi 12X",
      "price": 1100,
      "image01": "/images/products/28.png",
      "image02": "/images/products/29.png",
      "category": "xiaomi",
      "colors": [
        {
          "name": "blue",
          "price": 10
        },
        {
          "name": "green",
          "price": 5
        },
        {
          "name": "black",
          "price": 8
        }
      ],
      "config": {
        "ram": [
          {
            "value": "2g",
            "price": 9
          },
          {
            "value": "4g",
            "price": 11
          },
          {
            "value": "6g",
            "price": 15
          }
        ],
        "memory": "128",
        "material": "metal",
        "camera": "108mp",
        "battery": "4000 mAh",
        "display": "6.7",
        "internet": "5G"
      },
      "desc": "Lorem ipsum dolor sit amet consectetur adipisicing elit. Labore rerum laboriosam delectus ipsum doloremque eius expedita quis dolore. Accusamus ipsum nobis incidunt iure inventore aliquam, ullam autem quaerat, quas quasi nam excepturi maiores suscipit. Officia ratione fugit nam possimus assumenda qui aliquam totam voluptatum veniam! Incidunt deleniti totam reprehenderit, quasi cumque consectetur. Laboriosam ab nobis ratione. Sequi quia vitae, similique quod officiis sint adipisci voluptatum fugit assumenda quos accusamus numquam quisquam architecto ratione cum tenetur libero. Amet numquam sequi impedit obcaecati ducimus, fugit labore fuga dolorem quisquam. Itaque quisquam nostrum iste praesentium beatae voluptas inventore, voluptatibus, sapiente, quidem doloremque assumenda! ",
      "created_at": "2022/8/22",
      "quantity": 1
    }
  ],
  "discounts": [
    {
      "code": "mehr1401",
      "value": 40
    }
  ]
}